mojoRPG/__init__.py
mojoRPG/__main__.py
mojoRPG/mojo/__init__.py
mojoRPG/mojo/character.py
mojoRPG/mojo/game.py
mojoRPG/mojo/mojocore.py
mojoRPG-0.0.10.dist-info/METADATA
mojoRPG-0.0.10.dist-info/WHEEL
mojoRPG-0.0.10.dist-info/top_level.txt
mojoRPG-0.0.10.dist-info/RECORD
